awkg/__init__.py
awkg/__main__.py
awkg/awkg.py
awkg-0.3.0.dist-info/LICENSE
awkg-0.3.0.dist-info/METADATA
awkg-0.3.0.dist-info/WHEEL
awkg-0.3.0.dist-info/entry_points.txt
awkg-0.3.0.dist-info/top_level.txt
awkg-0.3.0.dist-info/RECORD
