Metadata-Version: 2.1
Name: awkg
Version: 0.3.0
Summary: awkg is an awk-like text-processing tool powered by python language
Home-page: https://github.com/thammegowda/awkg
Author: Thamme Gowda
Author-email: tgowdan@gmail.com
License: GNU General Public License v3 (GPLv3)
Download-URL: https://github.com/thammegowda/awkg
Platform: any
Classifier: Development Status :: 5 - Production/Stable
Classifier: Intended Audience :: Developers
Classifier: Topic :: Text Processing
Classifier: Topic :: Utilities
Classifier: Topic :: Text Processing :: General
Classifier: Topic :: Text Processing :: Filters
Classifier: License :: OSI Approved :: GNU General Public License v3 (GPLv3)
Classifier: Programming Language :: Python :: 3
Requires-Python: >=3.5
